setup.py
somweather/__init__.py
somweather/somweather.py
somweather.egg-info/PKG-INFO
somweather.egg-info/SOURCES.txt
somweather.egg-info/dependency_links.txt
somweather.egg-info/requires.txt
somweather.egg-info/top_level.txt