Metadata-Version: 2.1
Name: somweather
Version: 0.0.1
Summary: test app
Home-page: 
Author: Sominya
Author-email: sbajpai@deloitte.com
License: MIT
